fetchbib/__init__.py
fetchbib/cli.py
fetchbib/config.py
fetchbib/formatter.py
fetchbib/resolver.py
fetchbib-0.6.0.dist-info/licenses/LICENSE
fetchbib-0.6.0.dist-info/METADATA
fetchbib-0.6.0.dist-info/WHEEL
fetchbib-0.6.0.dist-info/entry_points.txt
fetchbib-0.6.0.dist-info/top_level.txt
fetchbib-0.6.0.dist-info/RECORD
