Metadata-Version: 2.4
Name: fetchbib
Version: 0.6.0
Summary: Resolve DOIs and search queries into formatted BibTeX entries.
Author: Matthew DeVerna
License-Expression: MIT
Project-URL: Homepage, https://github.com/mr-devs/fetchbib
Project-URL: Repository, https://github.com/mr-devs/fetchbib
Project-URL: Issues, https://github.com/mr-devs/fetchbib/issues
Requires-Python: >=3.9
License-File: LICENSE
Requires-Dist: requests
Dynamic: license-file
